core_auth/__init__.py
core_auth/py.typed
core_auth/auth/__init__.py
core_auth/auth/jwt_token/__init__.py
core_auth/auth/jwt_token/algorithm.py
core_auth/auth/jwt_token/jwt_auth.py
core_auth-1.0.1.dist-info/licenses/LICENSE
core_auth-1.0.1.dist-info/METADATA
core_auth-1.0.1.dist-info/WHEEL
core_auth-1.0.1.dist-info/top_level.txt
core_auth-1.0.1.dist-info/RECORD
